{
  "help": "https://catalog.data.metro.tokyo.lg.jp/api/3/action/help_show?name=package_show",
  "success": true,
  "result": {
    "license_title": "クリエイティブ・コモンズ 表示（CC BY）",
    "maintainer": "東京都福祉保健局健康安全部感染症対策課",
    "relationships_as_object": [],
    "private": false,
    "maintainer_email": null,
    "num_tags": 0,
    "id": "0b1dd4e1-896b-4750-bd8d-9acf99d1f8bd",
    "metadata_created": "2021-05-21T02:25:18.038438",
    "metadata_modified": "2021-06-08T08:51:35.906759",
    "author": null,
    "author_email": null,
    "state": "active",
    "version": null,
    "creator_user_id": "759cdcb3-5319-491c-838e-590e17c52b90",
    "type": "dataset",
    "resources": [
      {
        "mimetype": null,
        "cache_url": null,
        "hash": "",
        "description": "",
        "name": "表３ 東京都のエイズ対策予算の推移（平成 11(1999)年度～平成 20(2008)年度）",
        "format": "CSV",
        "url": "https://www.opendata.metro.tokyo.lg.jp/fukushihoken/R3/siryo2_01.csv",
        "cache_last_updated": null,
        "package_id": "0b1dd4e1-896b-4750-bd8d-9acf99d1f8bd",
        "created": "2021-03-10T09:07:00",
        "state": "active",
        "mimetype_inner": null,
        "last_modified": "2021-03-10T09:07:00",
        "position": 0,
        "revision_id": "ae02eafc-e7ec-4192-9332-daf350efa717",
        "url_type": null,
        "id": "c19c9da9-32e5-4f74-8ec8-11a72b1c024d",
        "resource_type": null,
        "size": 777
      },
      {
        "mimetype": null,
        "cache_url": null,
        "hash": "",
        "description": "",
        "name": "表４ エイズ啓発拠点「ふぉー・てぃー」実績（平成 18(2006)年度～平成 20(2008)年度）",
        "format": "CSV",
        "url": "https://www.opendata.metro.tokyo.lg.jp/fukushihoken/R3/siryo2_02.csv",
        "cache_last_updated": null,
        "package_id": "0b1dd4e1-896b-4750-bd8d-9acf99d1f8bd",
        "created": "2021-03-10T09:18:00",
        "state": "active",
        "mimetype_inner": null,
        "last_modified": "2021-03-10T09:18:00",
        "position": 1,
        "revision_id": "804330ad-1b66-43f3-b3fb-c9c88ee499c8",
        "url_type": null,
        "id": "da3b9bfd-0e1c-40c5-ba95-bc6db470ae6c",
        "resource_type": null,
        "size": 310
      },
      {
        "mimetype": null,
        "cache_url": null,
        "hash": "",
        "description": "",
        "name": "図８ 全国の年代別「発症後にＨＩＶ感染が分かる事例」の割合（平成 19(2007)年）",
        "format": "CSV",
        "url": "https://www.opendata.metro.tokyo.lg.jp/fukushihoken/R3/siryo3_01.csv",
        "cache_last_updated": null,
        "package_id": "0b1dd4e1-896b-4750-bd8d-9acf99d1f8bd",
        "created": "2021-03-10T09:33:00",
        "state": "active",
        "mimetype_inner": null,
        "last_modified": "2021-03-10T09:33:00",
        "position": 2,
        "revision_id": "9b644c68-12a2-4c71-a92f-a179d7f8d429",
        "url_type": null,
        "id": "9629e1e9-9d2e-4473-afe3-397941a233ea",
        "resource_type": null,
        "size": 196
      },
      {
        "mimetype": null,
        "cache_url": null,
        "hash": "",
        "description": "",
        "name": "図１５ 東京都の年代別「発症後にＨＩＶ感染が分かる事例」の割合（平成 19(2007)年）",
        "format": "CSV",
        "url": "https://www.opendata.metro.tokyo.lg.jp/fukushihoken/R3/siryo3_02.csv",
        "cache_last_updated": null,
        "package_id": "0b1dd4e1-896b-4750-bd8d-9acf99d1f8bd",
        "created": "2021-03-10T09:41:00",
        "state": "active",
        "mimetype_inner": null,
        "last_modified": "2021-03-10T09:41:00",
        "position": 3,
        "revision_id": "9b644c68-12a2-4c71-a92f-a179d7f8d429",
        "url_type": null,
        "id": "1750a62c-6a8d-486f-9ffe-38c6597f6ac8",
        "resource_type": null,
        "size": 188
      },
      {
        "mimetype": null,
        "cache_url": null,
        "hash": "",
        "description": "",
        "name": "表６ 東京都の外国籍ＨＩＶ感染者及びエイズ患者の国籍（平成 15(2003)年～平成 19(2007)年）累積数 ",
        "format": "CSV",
        "url": "https://www.opendata.metro.tokyo.lg.jp/fukushihoken/R3/siryo3_03.csv",
        "cache_last_updated": null,
        "package_id": "0b1dd4e1-896b-4750-bd8d-9acf99d1f8bd",
        "created": "2021-03-10T09:50:00",
        "state": "active",
        "mimetype_inner": null,
        "last_modified": "2021-03-10T09:50:00",
        "position": 4,
        "revision_id": "9b644c68-12a2-4c71-a92f-a179d7f8d429",
        "url_type": null,
        "id": "99d71d32-6262-4ffc-90e6-80207003413e",
        "resource_type": null,
        "size": 685
      },
      {
        "mimetype": null,
        "cache_url": null,
        "hash": "",
        "description": "",
        "name": "図２５ 新宿２丁目における予防啓発の効果（アンケート調査結果より）",
        "format": "CSV",
        "url": "https://www.opendata.metro.tokyo.lg.jp/fukushihoken/R3/siryo4_01.csv",
        "cache_last_updated": null,
        "package_id": "0b1dd4e1-896b-4750-bd8d-9acf99d1f8bd",
        "created": "2021-03-10T10:07:00",
        "state": "active",
        "mimetype_inner": null,
        "last_modified": "2021-03-10T10:07:00",
        "position": 5,
        "revision_id": "9b644c68-12a2-4c71-a92f-a179d7f8d429",
        "url_type": null,
        "id": "b85c418c-53ef-42c1-babc-90af5dcd229e",
        "resource_type": null,
        "size": 129
      },
      {
        "mimetype": null,
        "cache_url": null,
        "hash": "",
        "description": "",
        "name": "図２７ 都内の行政機関が実施するＨＩＶ検査件数・陽性件数（平成 11(1999)年～平成 19(2007)年）",
        "format": "CSV",
        "url": "https://www.opendata.metro.tokyo.lg.jp/fukushihoken/R3/siryo5_01.csv",
        "cache_last_updated": null,
        "package_id": "0b1dd4e1-896b-4750-bd8d-9acf99d1f8bd",
        "created": "2021-03-10T10:17:00",
        "state": "active",
        "mimetype_inner": null,
        "last_modified": "2021-03-10T10:17:00",
        "position": 6,
        "revision_id": "000d12c5-2479-4bee-8ada-976ab6297bc0",
        "url_type": null,
        "id": "d53f8ed3-6386-4349-b50b-ad96f494f871",
        "resource_type": null,
        "size": 527
      },
      {
        "mimetype": null,
        "cache_url": null,
        "hash": "",
        "description": "",
        "name": "図３０ 島しょ・多摩地域保健所、東京都南新宿検査･相談室の男女別年代別受検者数（平成 19 年アンケート集計結果より）",
        "format": "CSV",
        "url": "https://www.opendata.metro.tokyo.lg.jp/fukushihoken/R3/siryo5_02.csv",
        "cache_last_updated": null,
        "package_id": "0b1dd4e1-896b-4750-bd8d-9acf99d1f8bd",
        "created": "2021-03-10T10:22:00",
        "state": "active",
        "mimetype_inner": null,
        "last_modified": "2021-03-10T10:22:00",
        "position": 7,
        "revision_id": "000d12c5-2479-4bee-8ada-976ab6297bc0",
        "url_type": null,
        "id": "c0f7c5fd-1a68-4e1a-9655-7dd52219244b",
        "resource_type": null,
        "size": 358
      },
      {
        "mimetype": null,
        "cache_url": null,
        "hash": "",
        "description": "",
        "name": "図３１ 東京都南新宿検査･相談室、東京都多摩地域検査･相談室、島しょ・多摩地域保健所の職業別受検者割合の比較（平成 19 年アンケート集計結果より）",
        "format": "CSV",
        "url": "https://www.opendata.metro.tokyo.lg.jp/fukushihoken/R3/siryo5_03.csv",
        "cache_last_updated": null,
        "package_id": "0b1dd4e1-896b-4750-bd8d-9acf99d1f8bd",
        "created": "2021-03-10T10:23:00",
        "state": "active",
        "mimetype_inner": null,
        "last_modified": "2021-03-10T10:23:00",
        "position": 8,
        "revision_id": "000d12c5-2479-4bee-8ada-976ab6297bc0",
        "url_type": null,
        "id": "412c1f0a-5408-43df-9d23-2aa9a8fadfd7",
        "resource_type": null,
        "size": 199
      },
      {
        "mimetype": null,
        "cache_url": null,
        "hash": "",
        "description": "",
        "name": "図３２ 東京都多摩地域検査・相談室における即日（迅速）検査の実績（平成 17(2005)年度～平成 19(2007)年度）",
        "format": "CSV",
        "url": "https://www.opendata.metro.tokyo.lg.jp/fukushihoken/R3/siryo5_04.csv",
        "cache_last_updated": null,
        "package_id": "0b1dd4e1-896b-4750-bd8d-9acf99d1f8bd",
        "created": "2021-03-10T10:24:00",
        "state": "active",
        "mimetype_inner": null,
        "last_modified": "2021-03-10T10:24:00",
        "position": 9,
        "revision_id": "000d12c5-2479-4bee-8ada-976ab6297bc0",
        "url_type": null,
        "id": "954801df-b539-45be-94a2-d7f3f8f8a4de",
        "resource_type": null,
        "size": 65
      },
      {
        "mimetype": null,
        "cache_url": null,
        "hash": "",
        "description": "",
        "name": "図３３ 東京都エイズ電話相談実績（平成 19(2007)年度）",
        "format": "CSV",
        "url": "https://www.opendata.metro.tokyo.lg.jp/fukushihoken/R3/siryo5_05.csv",
        "cache_last_updated": null,
        "package_id": "0b1dd4e1-896b-4750-bd8d-9acf99d1f8bd",
        "created": "2021-03-11T00:16:00",
        "state": "active",
        "mimetype_inner": null,
        "last_modified": "2021-03-11T00:16:00",
        "position": 10,
        "revision_id": "000d12c5-2479-4bee-8ada-976ab6297bc0",
        "url_type": null,
        "id": "e3a2b71b-6e8f-49dc-939c-534a620ab62e",
        "resource_type": null,
        "size": 79
      },
      {
        "mimetype": null,
        "cache_url": null,
        "hash": "",
        "description": "",
        "name": "図３４ エイズ診療拠点病院 外来・入院延べ数年次推移（平成 14(2002)年度～平成 19(2007)年度）",
        "format": "CSV",
        "url": "https://www.opendata.metro.tokyo.lg.jp/fukushihoken/R3/siryo6_01.csv",
        "cache_last_updated": null,
        "package_id": "0b1dd4e1-896b-4750-bd8d-9acf99d1f8bd",
        "created": "2021-03-11T00:25:00",
        "state": "active",
        "mimetype_inner": null,
        "last_modified": "2021-03-11T00:25:00",
        "position": 11,
        "revision_id": "d86420a7-4ad2-44a2-99cc-1702dbe32097",
        "url_type": null,
        "id": "240c79b8-74db-44fd-a90e-f9365f6fede6",
        "resource_type": null,
        "size": 184
      },
      {
        "mimetype": null,
        "cache_url": null,
        "hash": "",
        "description": "",
        "name": "図３５ 外来実績の多い４病院の割合（平成 19(2007)年度）",
        "format": "CSV",
        "url": "https://www.opendata.metro.tokyo.lg.jp/fukushihoken/R3/siryo6_02.csv",
        "cache_last_updated": null,
        "package_id": "0b1dd4e1-896b-4750-bd8d-9acf99d1f8bd",
        "created": "2021-03-11T00:46:00",
        "state": "active",
        "mimetype_inner": null,
        "last_modified": "2021-03-11T00:46:00",
        "position": 12,
        "revision_id": "d86420a7-4ad2-44a2-99cc-1702dbe32097",
        "url_type": null,
        "id": "e9e2f508-9dea-4417-ba17-eb0043606c93",
        "resource_type": null,
        "size": 66
      },
      {
        "mimetype": null,
        "cache_url": null,
        "hash": "",
        "description": "",
        "name": "図３６ 東京都の HIV 感染者及びエイズ患者の累積報告数と身体障害者手帳(免疫機能障害)交付数（平成 10(1998)年～平成 19(2007)年）",
        "format": "CSV",
        "url": "https://www.opendata.metro.tokyo.lg.jp/fukushihoken/R3/siryo6_03.csv",
        "cache_last_updated": null,
        "package_id": "0b1dd4e1-896b-4750-bd8d-9acf99d1f8bd",
        "created": "2021-03-11T00:47:00",
        "state": "active",
        "mimetype_inner": null,
        "last_modified": "2021-03-11T00:47:00",
        "position": 13,
        "revision_id": "d86420a7-4ad2-44a2-99cc-1702dbe32097",
        "url_type": null,
        "id": "e042c4e4-a26c-4866-a7b8-37b623ef65ae",
        "resource_type": null,
        "size": 259
      }
    ],
    "num_resources": 14,
    "tags": [],
    "groups": [],
    "license_id": "CC-BY-4.0",
    "relationships_as_subject": [],
    "organization": {
      "description": "http://www.fukushihoken.metro.tokyo.jp/\r\n\r\n所属:東京都",
      "created": "2019-11-01T03:27:20.864364",
      "title": "東京都福祉保健局",
      "name": "t000010",
      "is_organization": true,
      "state": "active",
      "image_url": "https://catalog.data.metro.tokyo.lg.jp/tokyo_od_theme/images/organization/t000010.jpg",
      "revision_id": "8d3da6a9-bfe7-4cd1-9d5d-9737b2293939",
      "type": "organization",
      "id": "78dce3df-d79a-4379-97d1-6f6b8b25039a",
      "approval_status": "approved"
    },
    "name": "t000010d2000000096",
    "isopen": true,
    "url": "http://www.fukushihoken.metro.tokyo.jp/iryo/kansen/aids/sennmonnkakaigi/houkoku.files/siryo2.pdf",
    "notes": "",
    "owner_org": "78dce3df-d79a-4379-97d1-6f6b8b25039a",
    "extras": [
      {
        "key": "更新頻度",
        "value": "随時"
      }
    ],
    "license_url": "https://creativecommons.org/licenses/by/4.0/deed.ja",
    "title": "東京都エイズ専門家会議「最終報告」について_「東京都におけるエイズ対策の現状　～現在の課題と今後の方向性～　資料編」（2）（PDF：123KB）",
    "revision_id": "87f6aea5-e071-49ac-a4b1-97b9ba603143"
  }
}
