{
  "help": "https://catalog.data.metro.tokyo.lg.jp/api/3/action/help_show?name=package_show",
  "success": true,
  "result": {
    "license_title": "クリエイティブ・コモンズ 表示（CC BY）",
    "maintainer": "政策経営部IT推進課",
    "relationships_as_object": [],
    "private": false,
    "maintainer_email": null,
    "num_tags": 0,
    "id": "110b8f28-f690-45bb-8475-1c5709aad45f",
    "metadata_created": "2021-03-18T07:38:07.370981",
    "metadata_modified": "2021-03-18T07:38:47.258557",
    "author": null,
    "author_email": null,
    "state": "active",
    "version": null,
    "creator_user_id": "759cdcb3-5319-491c-838e-590e17c52b90",
    "type": "dataset",
    "resources": [
      {
        "mimetype": null,
        "cache_url": null,
        "hash": "",
        "description": "環境学習に関するデータです。",
        "name": "環境学習",
        "format": "CSV",
        "url": "https://www.city.itabashi.tokyo.jp/_res/projects/default_project/_page_/001/031/246/attach_89544_2.csv",
        "cache_last_updated": null,
        "package_id": "110b8f28-f690-45bb-8475-1c5709aad45f",
        "created": "2021-03-18T07:38:24.978430",
        "state": "active",
        "mimetype_inner": null,
        "last_modified": null,
        "position": 0,
        "revision_id": "d75bc4c3-6c93-4b54-a9e9-508115535cc2",
        "url_type": null,
        "id": "b741d81c-6e72-4e88-a4b0-7f342919c96e",
        "resource_type": null,
        "size": 692224
      },
      {
        "mimetype": null,
        "cache_url": null,
        "hash": "",
        "description": "植物園に関するデータです。",
        "name": "植物園",
        "format": "CSV",
        "url": "https://www.city.itabashi.tokyo.jp/_res/projects/default_project/_page_/001/031/246/attach_89544_3.csv",
        "cache_last_updated": null,
        "package_id": "110b8f28-f690-45bb-8475-1c5709aad45f",
        "created": "2021-03-18T07:38:25.244264",
        "state": "active",
        "mimetype_inner": null,
        "last_modified": null,
        "position": 1,
        "revision_id": "585443b3-0d5e-4abd-bc94-fbab9a78a641",
        "url_type": null,
        "id": "9ef6d3f3-5321-4767-a62c-7881a0bdadde",
        "resource_type": null,
        "size": null
      },
      {
        "mimetype": null,
        "cache_url": null,
        "hash": "",
        "description": "清掃・公園事務所に関するデータです。",
        "name": "清掃・公園事務所",
        "format": "CSV",
        "url": "https://www.city.itabashi.tokyo.jp/_res/projects/default_project/_page_/001/031/246/attach_89544_4.csv",
        "cache_last_updated": null,
        "package_id": "110b8f28-f690-45bb-8475-1c5709aad45f",
        "created": "2021-03-18T07:38:25.515933",
        "state": "active",
        "mimetype_inner": null,
        "last_modified": null,
        "position": 2,
        "revision_id": "875b959f-181f-45ee-8b2a-86ae3735b8a8",
        "url_type": null,
        "id": "4bef4c86-b299-49e9-8657-25a52b21e170",
        "resource_type": null,
        "size": null
      },
      {
        "mimetype": null,
        "cache_url": null,
        "hash": "",
        "description": "防災避難所に関するデータです。",
        "name": "防災避難所",
        "format": "CSV",
        "url": "https://www.city.itabashi.tokyo.jp/_res/projects/default_project/_page_/001/031/246/attach_89544_5.csv",
        "cache_last_updated": null,
        "package_id": "110b8f28-f690-45bb-8475-1c5709aad45f",
        "created": "2021-03-18T07:38:25.797462",
        "state": "active",
        "mimetype_inner": null,
        "last_modified": null,
        "position": 3,
        "revision_id": "3e5d581f-6012-4125-8c71-189a7c4cdb8d",
        "url_type": null,
        "id": "73ab38ac-cdbb-4973-9c4c-0888a70d8b0f",
        "resource_type": null,
        "size": 18329
      },
      {
        "mimetype": null,
        "cache_url": null,
        "hash": "",
        "description": "帰宅困難者の一時滞在施設に関するデータです。",
        "name": "帰宅困難者の一時滞在施設",
        "format": "CSV",
        "url": "https://www.city.itabashi.tokyo.jp/_res/projects/default_project/_page_/001/031/246/attach_89544_6.csv",
        "cache_last_updated": null,
        "package_id": "110b8f28-f690-45bb-8475-1c5709aad45f",
        "created": "2021-03-18T07:38:26.073522",
        "state": "active",
        "mimetype_inner": null,
        "last_modified": null,
        "position": 4,
        "revision_id": "2cb0bd6e-7937-48a4-8622-161221b2bca4",
        "url_type": null,
        "id": "6264f4c2-0e3a-48a7-a444-d985c96fbe87",
        "resource_type": null,
        "size": null
      },
      {
        "mimetype": null,
        "cache_url": null,
        "hash": "",
        "description": "ＬＥＤ（街灯）に関するデータです。",
        "name": "ＬＥＤ（街灯）",
        "format": "CSV",
        "url": "https://www.city.itabashi.tokyo.jp/_res/projects/default_project/_page_/001/031/246/attach_89544_7.csv",
        "cache_last_updated": null,
        "package_id": "110b8f28-f690-45bb-8475-1c5709aad45f",
        "created": "2021-03-18T07:38:26.406200",
        "state": "active",
        "mimetype_inner": null,
        "last_modified": null,
        "position": 5,
        "revision_id": "189582ad-38ba-464c-a0e2-82d47d9d1106",
        "url_type": null,
        "id": "8e468200-c457-4c99-8d26-1776ad29e6ca",
        "resource_type": null,
        "size": 410624
      }
    ],
    "num_resources": 6,
    "tags": [],
    "groups": [],
    "license_id": "CC-BY-4.0",
    "relationships_as_subject": [],
    "organization": {
      "description": "http://www.city.itabashi.tokyo.jp/",
      "created": "2019-11-01T03:27:25.673886",
      "title": "板橋区",
      "name": "t131199",
      "is_organization": true,
      "state": "active",
      "image_url": "https://catalog.data.metro.tokyo.lg.jp/tokyo_od_theme/images/organization/t131199.jpg",
      "revision_id": "1a86d48e-188d-4655-9cc5-c9aedb102db4",
      "type": "organization",
      "id": "9354a576-4de5-44ab-9e62-18a92b40b5e7",
      "approval_status": "approved"
    },
    "name": "t131199d0000000152",
    "isopen": true,
    "url": "https://www.city.itabashi.tokyo.jp/kusei/joho/sisetsu/1031246.html",
    "notes": "【板橋区】どこナビいたばし（地図）で掲載している地理情報のうち、環境・防災に関するデータを掲載しています。",
    "owner_org": "9354a576-4de5-44ab-9e62-18a92b40b5e7",
    "extras": [
      {
        "key": "更新頻度",
        "value": "随時"
      }
    ],
    "license_url": "https://creativecommons.org/licenses/by/4.0/deed.ja",
    "title": "環境・防災",
    "revision_id": "c5b13395-c9f3-4e28-87df-a4ce7783f2d6"
  }
}
