{
  "help": "https://catalog.data.metro.tokyo.lg.jp/api/3/action/help_show?name=package_show",
  "success": true,
  "result": {
    "license_title": "クリエイティブ・コモンズ 表示（CC BY）",
    "maintainer": "行政改革推進部",
    "relationships_as_object": [],
    "private": false,
    "maintainer_email": null,
    "num_tags": 0,
    "id": "a97d7051-ca54-4d35-b749-93ee013ab27b",
    "metadata_created": "2020-06-10T05:44:48.902456",
    "metadata_modified": "2020-06-10T05:44:59.463546",
    "author": null,
    "author_email": null,
    "state": "active",
    "version": null,
    "creator_user_id": "759cdcb3-5319-491c-838e-590e17c52b90",
    "type": "dataset",
    "resources": [
      {
        "mimetype": null,
        "cache_url": null,
        "hash": "",
        "description": "",
        "name": "東京都版市場化テストモデル事業モニタリング結果（平成１９年度後期分）",
        "format": "CSV",
        "url": "https://www.opendata.metro.tokyo.lg.jp/soumu/h31/toukyoutoban.csv",
        "cache_last_updated": null,
        "package_id": "a97d7051-ca54-4d35-b749-93ee013ab27b",
        "created": "2020-03-30T15:00:00",
        "state": "active",
        "mimetype_inner": null,
        "last_modified": "2020-03-30T15:00:00",
        "position": 0,
        "revision_id": "1b1cb58a-8b54-4d2d-868e-01ab06721a8a",
        "url_type": null,
        "id": "0f7d8e41-970f-4daa-a12b-1cec159d2ed9",
        "resource_type": null,
        "size": null
      },
      {
        "mimetype": null,
        "cache_url": null,
        "hash": "",
        "description": "",
        "name": "ネットワーク構築科（中央・城北センター有明分校） ",
        "format": "CSV",
        "url": "https://www.opendata.metro.tokyo.lg.jp/soumu/h31/netto(ari).csv",
        "cache_last_updated": null,
        "package_id": "a97d7051-ca54-4d35-b749-93ee013ab27b",
        "created": "2020-03-30T15:00:00",
        "state": "active",
        "mimetype_inner": null,
        "last_modified": "2020-03-30T15:00:00",
        "position": 1,
        "revision_id": "dbfa88f8-a8ec-4724-8a1f-6a702455e49f",
        "url_type": null,
        "id": "627c6502-41bd-4af2-94f8-07e0d33d087a",
        "resource_type": null,
        "size": null
      },
      {
        "mimetype": null,
        "cache_url": null,
        "hash": "",
        "description": "",
        "name": "ネットワーク構築（有明）",
        "format": "CSV",
        "url": "https://www.opendata.metro.tokyo.lg.jp/soumu/h31/netto(ari)g.csv",
        "cache_last_updated": null,
        "package_id": "a97d7051-ca54-4d35-b749-93ee013ab27b",
        "created": "2020-03-30T15:00:00",
        "state": "active",
        "mimetype_inner": null,
        "last_modified": "2020-03-30T15:00:00",
        "position": 2,
        "revision_id": "396e1c3c-ef8a-411d-8d40-91bfbdd46c6f",
        "url_type": null,
        "id": "45cbca5e-50b4-42c1-8498-5911645df5f6",
        "resource_type": null,
        "size": null
      },
      {
        "mimetype": null,
        "cache_url": null,
        "hash": "",
        "description": "",
        "name": "貿易実務科（中央・城北センター有明分校）",
        "format": "CSV",
        "url": "https://www.opendata.metro.tokyo.lg.jp/soumu/h31/boueki(ari).csv",
        "cache_last_updated": null,
        "package_id": "a97d7051-ca54-4d35-b749-93ee013ab27b",
        "created": "2020-03-30T15:00:00",
        "state": "active",
        "mimetype_inner": null,
        "last_modified": "2020-03-30T15:00:00",
        "position": 3,
        "revision_id": "f69a95d2-818c-443c-a5c1-4207db4240ae",
        "url_type": null,
        "id": "984c9178-6fa7-40d3-85a4-6fac4c8ff37b",
        "resource_type": null,
        "size": null
      },
      {
        "mimetype": null,
        "cache_url": null,
        "hash": "",
        "description": "",
        "name": "貿易実務（有明）",
        "format": "CSV",
        "url": "https://www.opendata.metro.tokyo.lg.jp/soumu/h31/boueki(ari)g.csv",
        "cache_last_updated": null,
        "package_id": "a97d7051-ca54-4d35-b749-93ee013ab27b",
        "created": "2020-03-30T15:00:00",
        "state": "active",
        "mimetype_inner": null,
        "last_modified": "2020-03-30T15:00:00",
        "position": 4,
        "revision_id": "c5d9cded-f2a9-405f-8d5b-9e78d6379115",
        "url_type": null,
        "id": "7ab669a9-eaf8-4d82-a1d5-5cebe2db3821",
        "resource_type": null,
        "size": null
      },
      {
        "mimetype": null,
        "cache_url": null,
        "hash": "",
        "description": "",
        "name": "医療事務科（中央・城北センター）",
        "format": "CSV",
        "url": "https://www.opendata.metro.tokyo.lg.jp/soumu/h31/iryou(cyuu).csv",
        "cache_last_updated": null,
        "package_id": "a97d7051-ca54-4d35-b749-93ee013ab27b",
        "created": "2020-03-30T15:00:00",
        "state": "active",
        "mimetype_inner": null,
        "last_modified": "2020-03-30T15:00:00",
        "position": 5,
        "revision_id": "9374b5ad-f209-4031-b713-ce7c77bd7d81",
        "url_type": null,
        "id": "51a17a79-6fa7-47c1-b388-1f297538c0b8",
        "resource_type": null,
        "size": null
      },
      {
        "mimetype": null,
        "cache_url": null,
        "hash": "",
        "description": "",
        "name": "医療事務（中央・城北）",
        "format": "CSV",
        "url": "https://www.opendata.metro.tokyo.lg.jp/soumu/h31/iryou(cyuu)g.csv",
        "cache_last_updated": null,
        "package_id": "a97d7051-ca54-4d35-b749-93ee013ab27b",
        "created": "2020-03-30T15:00:00",
        "state": "active",
        "mimetype_inner": null,
        "last_modified": "2020-03-30T15:00:00",
        "position": 6,
        "revision_id": "09424858-070e-44d9-b639-f105ed1fe858",
        "url_type": null,
        "id": "f781ab25-b0d1-4ca5-8fdd-36cd34322898",
        "resource_type": null,
        "size": null
      },
      {
        "mimetype": null,
        "cache_url": null,
        "hash": "",
        "description": "",
        "name": "医療事務科（多摩センター八王子校）",
        "format": "CSV",
        "url": "https://www.opendata.metro.tokyo.lg.jp/soumu/h31/iryou(ha).csv",
        "cache_last_updated": null,
        "package_id": "a97d7051-ca54-4d35-b749-93ee013ab27b",
        "created": "2020-03-30T15:00:00",
        "state": "active",
        "mimetype_inner": null,
        "last_modified": "2020-03-30T15:00:00",
        "position": 7,
        "revision_id": "a0aee444-6790-4cff-a4fc-4ffd204acb4e",
        "url_type": null,
        "id": "e602451b-2db4-4b80-926a-b522956fcdda",
        "resource_type": null,
        "size": null
      },
      {
        "mimetype": null,
        "cache_url": null,
        "hash": "",
        "description": "",
        "name": "医療事務（八王子）",
        "format": "CSV",
        "url": "https://www.opendata.metro.tokyo.lg.jp/soumu/h31/iryou(ha)g.csv",
        "cache_last_updated": null,
        "package_id": "a97d7051-ca54-4d35-b749-93ee013ab27b",
        "created": "2020-03-30T15:00:00",
        "state": "active",
        "mimetype_inner": null,
        "last_modified": "2020-03-30T15:00:00",
        "position": 8,
        "revision_id": "82605806-91c1-4a5f-8179-7f428dd72df4",
        "url_type": null,
        "id": "456ef9ca-5f31-4256-be76-926172629a69",
        "resource_type": null,
        "size": null
      },
      {
        "mimetype": null,
        "cache_url": null,
        "hash": "",
        "description": "",
        "name": "ビジネス経理科（中央・城北センター高年齢者校）",
        "format": "CSV",
        "url": "https://www.opendata.metro.tokyo.lg.jp/soumu/h31/bizikei(kou).csv",
        "cache_last_updated": null,
        "package_id": "a97d7051-ca54-4d35-b749-93ee013ab27b",
        "created": "2020-03-30T15:00:00",
        "state": "active",
        "mimetype_inner": null,
        "last_modified": "2020-03-30T15:00:00",
        "position": 9,
        "revision_id": "88f11b09-0c9f-4c70-92d9-93a2df9e6bc6",
        "url_type": null,
        "id": "3419b2d0-80da-4297-95a2-9af9d5c9cb28",
        "resource_type": null,
        "size": null
      },
      {
        "mimetype": null,
        "cache_url": null,
        "hash": "",
        "description": "",
        "name": "ビジネス経理（高年齢者）",
        "format": "CSV",
        "url": "https://www.opendata.metro.tokyo.lg.jp/soumu/h31/bizikei(kou)g.csv",
        "cache_last_updated": null,
        "package_id": "a97d7051-ca54-4d35-b749-93ee013ab27b",
        "created": "2020-03-30T15:00:00",
        "state": "active",
        "mimetype_inner": null,
        "last_modified": "2020-03-30T15:00:00",
        "position": 10,
        "revision_id": "1b1bf8ad-19c4-4f57-b1eb-66b1970cce4a",
        "url_type": null,
        "id": "b5929ab4-311d-48be-a5ab-8667b4b2837f",
        "resource_type": null,
        "size": null
      },
      {
        "mimetype": null,
        "cache_url": null,
        "hash": "",
        "description": "",
        "name": "経営管理実務科（中央・城北センター高年齢者校）",
        "format": "CSV",
        "url": "https://www.opendata.metro.tokyo.lg.jp/soumu/h31/keikan(kou).csv",
        "cache_last_updated": null,
        "package_id": "a97d7051-ca54-4d35-b749-93ee013ab27b",
        "created": "2020-03-30T15:00:00",
        "state": "active",
        "mimetype_inner": null,
        "last_modified": "2020-03-30T15:00:00",
        "position": 11,
        "revision_id": "b8a75605-4629-427d-843e-1e1aca75da52",
        "url_type": null,
        "id": "21edc2ac-f6a8-40d4-a947-32801ddd6564",
        "resource_type": null,
        "size": null
      },
      {
        "mimetype": null,
        "cache_url": null,
        "hash": "",
        "description": "",
        "name": "経営管理実務（高年齢者）",
        "format": "CSV",
        "url": "https://www.opendata.metro.tokyo.lg.jp/soumu/h31/keikan(kou)g.csv",
        "cache_last_updated": null,
        "package_id": "a97d7051-ca54-4d35-b749-93ee013ab27b",
        "created": "2020-03-30T15:00:00",
        "state": "active",
        "mimetype_inner": null,
        "last_modified": "2020-03-30T15:00:00",
        "position": 12,
        "revision_id": "6e539a37-269c-45ea-9eb4-fd83a83bb452",
        "url_type": null,
        "id": "f7596fcd-7871-4d9d-bae9-7e46a2efff7c",
        "resource_type": null,
        "size": null
      },
      {
        "mimetype": null,
        "cache_url": null,
        "hash": "",
        "description": "",
        "name": "経営管理実務科（多摩センター府中校）",
        "format": "CSV",
        "url": "https://www.opendata.metro.tokyo.lg.jp/soumu/h31/keikan(hu).csv",
        "cache_last_updated": null,
        "package_id": "a97d7051-ca54-4d35-b749-93ee013ab27b",
        "created": "2020-03-30T15:00:00",
        "state": "active",
        "mimetype_inner": null,
        "last_modified": "2020-03-30T15:00:00",
        "position": 13,
        "revision_id": "2e97ec2e-e570-413a-92e1-dca0167b6a17",
        "url_type": null,
        "id": "955008ce-8301-4985-b294-e44041e79ed2",
        "resource_type": null,
        "size": null
      },
      {
        "mimetype": null,
        "cache_url": null,
        "hash": "",
        "description": "",
        "name": "経営管理実務（府中）",
        "format": "CSV",
        "url": "https://www.opendata.metro.tokyo.lg.jp/soumu/h31/keikan(hu)g.csv",
        "cache_last_updated": null,
        "package_id": "a97d7051-ca54-4d35-b749-93ee013ab27b",
        "created": "2020-03-30T15:00:00",
        "state": "active",
        "mimetype_inner": null,
        "last_modified": "2020-03-30T15:00:00",
        "position": 14,
        "revision_id": "f2fa609a-216b-4acb-8bcf-8c601ec73184",
        "url_type": null,
        "id": "538d93e6-356d-4bba-a74e-d64a2bb2f61b",
        "resource_type": null,
        "size": null
      },
      {
        "mimetype": null,
        "cache_url": null,
        "hash": "",
        "description": "",
        "name": "東京都版市場化テストモデル事業評価（平成１９年度前期・後期）",
        "format": "CSV",
        "url": "https://www.opendata.metro.tokyo.lg.jp/soumu/h31/hyoukah19.csv",
        "cache_last_updated": null,
        "package_id": "a97d7051-ca54-4d35-b749-93ee013ab27b",
        "created": "2020-03-30T15:00:00",
        "state": "active",
        "mimetype_inner": null,
        "last_modified": "2020-03-30T15:00:00",
        "position": 15,
        "revision_id": "4b961918-3092-4dfc-ba1f-4577030e296c",
        "url_type": null,
        "id": "6c555b6b-d911-4fe2-9613-15e257cf0afc",
        "resource_type": null,
        "size": null
      },
      {
        "mimetype": null,
        "cache_url": null,
        "hash": "",
        "description": "",
        "name": "（評価結果）",
        "format": "CSV",
        "url": "https://www.opendata.metro.tokyo.lg.jp/soumu/h31/hyoukakekka.csv",
        "cache_last_updated": null,
        "package_id": "a97d7051-ca54-4d35-b749-93ee013ab27b",
        "created": "2020-03-30T15:00:00",
        "state": "active",
        "mimetype_inner": null,
        "last_modified": "2020-03-30T15:00:00",
        "position": 16,
        "revision_id": "e1754b4d-1333-4096-aed9-d94b4ea353d8",
        "url_type": null,
        "id": "0187c140-d4c3-4448-8772-0d8a92e76818",
        "resource_type": null,
        "size": null
      },
      {
        "mimetype": null,
        "cache_url": null,
        "hash": "",
        "description": "",
        "name": "○ 調査の概要",
        "format": "CSV",
        "url": "https://www.opendata.metro.tokyo.lg.jp/soumu/h31/chosagaiyou.csv",
        "cache_last_updated": null,
        "package_id": "a97d7051-ca54-4d35-b749-93ee013ab27b",
        "created": "2020-03-30T15:00:00",
        "state": "active",
        "mimetype_inner": null,
        "last_modified": "2020-03-30T15:00:00",
        "position": 17,
        "revision_id": "54d3115a-42be-4c39-bca0-73adf3ed47ff",
        "url_type": null,
        "id": "17530a67-a8a3-4075-8c72-9d036e5c42c6",
        "resource_type": null,
        "size": null
      },
      {
        "mimetype": null,
        "cache_url": null,
        "hash": "",
        "description": "",
        "name": "問１－１ 役に立った訓練内容（複数回答可）",
        "format": "CSV",
        "url": "https://www.opendata.metro.tokyo.lg.jp/soumu/h31/kekka1-1.csv",
        "cache_last_updated": null,
        "package_id": "a97d7051-ca54-4d35-b749-93ee013ab27b",
        "created": "2020-03-30T15:00:00",
        "state": "active",
        "mimetype_inner": null,
        "last_modified": "2020-03-30T15:00:00",
        "position": 18,
        "revision_id": "87c16c24-0353-40e4-944b-ab1640f93edd",
        "url_type": null,
        "id": "e4f4b6b9-453c-4db8-b053-a3968e670ef0",
        "resource_type": null,
        "size": null
      },
      {
        "mimetype": null,
        "cache_url": null,
        "hash": "",
        "description": "",
        "name": "問１－２ 役に立たなかった訓練内容（複数回答可）",
        "format": "CSV",
        "url": "https://www.opendata.metro.tokyo.lg.jp/soumu/h31/kekka1-2.csv",
        "cache_last_updated": null,
        "package_id": "a97d7051-ca54-4d35-b749-93ee013ab27b",
        "created": "2020-03-30T15:00:00",
        "state": "active",
        "mimetype_inner": null,
        "last_modified": "2020-03-30T15:00:00",
        "position": 19,
        "revision_id": "32ecc493-c106-4c9d-9319-ee0a45883027",
        "url_type": null,
        "id": "2e5fe597-40ce-4fa9-870e-69d3f5816b74",
        "resource_type": null,
        "size": null
      },
      {
        "mimetype": null,
        "cache_url": null,
        "hash": "",
        "description": "",
        "name": "問１－３ 今回訓練を受けた学校の良かった点（複数回答可）",
        "format": "CSV",
        "url": "https://www.opendata.metro.tokyo.lg.jp/soumu/h31/kekka1-3.csv",
        "cache_last_updated": null,
        "package_id": "a97d7051-ca54-4d35-b749-93ee013ab27b",
        "created": "2020-03-30T15:00:00",
        "state": "active",
        "mimetype_inner": null,
        "last_modified": "2020-03-30T15:00:00",
        "position": 20,
        "revision_id": "eb1975c4-fb95-4993-bf1c-5627b319be17",
        "url_type": null,
        "id": "c08603bd-a0db-4e9d-a087-4773e2f0d05b",
        "resource_type": null,
        "size": null
      },
      {
        "mimetype": null,
        "cache_url": null,
        "hash": "",
        "description": "",
        "name": "問１－４ 今回訓練を受けた学校の良くなかった点（複数回答可）",
        "format": "CSV",
        "url": "https://www.opendata.metro.tokyo.lg.jp/soumu/h31/kekka1-4.csv",
        "cache_last_updated": null,
        "package_id": "a97d7051-ca54-4d35-b749-93ee013ab27b",
        "created": "2020-03-30T15:00:00",
        "state": "active",
        "mimetype_inner": null,
        "last_modified": "2020-03-30T15:00:00",
        "position": 21,
        "revision_id": "2c9f24db-d8df-4d76-99c1-9aee9e029a8c",
        "url_type": null,
        "id": "18ba82d3-11ba-428a-8671-a13c16886398",
        "resource_type": null,
        "size": null
      },
      {
        "mimetype": null,
        "cache_url": null,
        "hash": "",
        "description": "",
        "name": "問１－５ 今回受けた職業訓練は、全体として就職活動に役に立ったか",
        "format": "CSV",
        "url": "https://www.opendata.metro.tokyo.lg.jp/soumu/h31/kekka1-5.csv",
        "cache_last_updated": null,
        "package_id": "a97d7051-ca54-4d35-b749-93ee013ab27b",
        "created": "2020-03-30T15:00:00",
        "state": "active",
        "mimetype_inner": null,
        "last_modified": "2020-03-30T15:00:00",
        "position": 22,
        "revision_id": "605bd61a-b394-4b8d-a4ec-11602f0e0aef",
        "url_type": null,
        "id": "2fa6e25d-1874-450c-afd2-78ddc196449e",
        "resource_type": null,
        "size": null
      },
      {
        "mimetype": null,
        "cache_url": null,
        "hash": "",
        "description": "",
        "name": "問１－６ 今後、就職活動に役立てるために、取りたい資格があるか",
        "format": "CSV",
        "url": "https://www.opendata.metro.tokyo.lg.jp/soumu/h31/kekka1-6.csv",
        "cache_last_updated": null,
        "package_id": "a97d7051-ca54-4d35-b749-93ee013ab27b",
        "created": "2020-03-30T15:00:00",
        "state": "active",
        "mimetype_inner": null,
        "last_modified": "2020-03-30T15:00:00",
        "position": 23,
        "revision_id": "a36416e8-766c-4532-8dfe-cfb9c2f7515b",
        "url_type": null,
        "id": "fb768b3e-7b8f-4f9d-a050-b1ee248fff73",
        "resource_type": null,
        "size": null
      },
      {
        "mimetype": null,
        "cache_url": null,
        "hash": "",
        "description": "",
        "name": "問２－１ 現在の就職状況（アンケート回答時)",
        "format": "CSV",
        "url": "https://www.opendata.metro.tokyo.lg.jp/soumu/h31/kekka2-1.csv",
        "cache_last_updated": null,
        "package_id": "a97d7051-ca54-4d35-b749-93ee013ab27b",
        "created": "2020-03-30T15:00:00",
        "state": "active",
        "mimetype_inner": null,
        "last_modified": "2020-03-30T15:00:00",
        "position": 24,
        "revision_id": "691cc2e2-68de-4273-a0f1-be23d05f53ac",
        "url_type": null,
        "id": "e4f193b5-a609-4450-ab25-fab0d5b3d623",
        "resource_type": null,
        "size": null
      },
      {
        "mimetype": null,
        "cache_url": null,
        "hash": "",
        "description": "",
        "name": "問２－２ 勤務形態（希望） （就職決定者・求職活動中の者のみ)",
        "format": "CSV",
        "url": "https://www.opendata.metro.tokyo.lg.jp/soumu/h31/kekka2-2.csv",
        "cache_last_updated": null,
        "package_id": "a97d7051-ca54-4d35-b749-93ee013ab27b",
        "created": "2020-03-30T15:00:00",
        "state": "active",
        "mimetype_inner": null,
        "last_modified": "2020-03-30T15:00:00",
        "position": 25,
        "revision_id": "23c428dc-5105-435c-85a7-eb7000192b9d",
        "url_type": null,
        "id": "63625da0-7645-490a-b763-1810ae2c1f50",
        "resource_type": null,
        "size": null
      },
      {
        "mimetype": null,
        "cache_url": null,
        "hash": "",
        "description": "",
        "name": "問２－３ 就職先（希望就職先）と訓練との関連性 （就職決定者・求職活動中の者のみ)",
        "format": "CSV",
        "url": "https://www.opendata.metro.tokyo.lg.jp/soumu/h31/kekka2-3.csv",
        "cache_last_updated": null,
        "package_id": "a97d7051-ca54-4d35-b749-93ee013ab27b",
        "created": "2020-03-30T15:00:00",
        "state": "active",
        "mimetype_inner": null,
        "last_modified": "2020-03-30T15:00:00",
        "position": 26,
        "revision_id": "9db4f2bd-164b-4bf4-8024-49c5cc437199",
        "url_type": null,
        "id": "9bc3cb6d-9b05-4d0b-bfb9-65a34b8fb629",
        "resource_type": null,
        "size": null
      },
      {
        "mimetype": null,
        "cache_url": null,
        "hash": "",
        "description": "",
        "name": "問３－１ 訓練の募集を知ったきっかけ",
        "format": "CSV",
        "url": "https://www.opendata.metro.tokyo.lg.jp/soumu/h31/kekka3-1.csv",
        "cache_last_updated": null,
        "package_id": "a97d7051-ca54-4d35-b749-93ee013ab27b",
        "created": "2020-03-30T15:00:00",
        "state": "active",
        "mimetype_inner": null,
        "last_modified": "2020-03-30T15:00:00",
        "position": 27,
        "revision_id": "7ffcb5bd-0bb8-40cc-96e5-cd640953e30d",
        "url_type": null,
        "id": "2706cf5b-aa6a-4edd-98ec-0c5026fa3e3f",
        "resource_type": null,
        "size": null
      },
      {
        "mimetype": null,
        "cache_url": null,
        "hash": "",
        "description": "",
        "name": "問３－２ 求人情報入手方法",
        "format": "CSV",
        "url": "https://www.opendata.metro.tokyo.lg.jp/soumu/h31/kekka3-2.csv",
        "cache_last_updated": null,
        "package_id": "a97d7051-ca54-4d35-b749-93ee013ab27b",
        "created": "2020-03-30T15:00:00",
        "state": "active",
        "mimetype_inner": null,
        "last_modified": "2020-03-30T15:00:00",
        "position": 28,
        "revision_id": "cb855dbf-9f49-43b8-8cee-c8f78c320b39",
        "url_type": null,
        "id": "bd2632ce-569b-4638-a5b1-aa1a74defc0e",
        "resource_type": null,
        "size": null
      }
    ],
    "num_resources": 29,
    "tags": [],
    "groups": [
      {
        "display_name": "産業雇用創出",
        "description": "",
        "image_display_url": "https://catalog.data.metro.tokyo.lg.jp/tokyo_od_theme/images/group/c011.png",
        "title": "産業雇用創出",
        "id": "bb1c42ce-dc7e-48cf-91d4-05cab59db4bd",
        "name": "c011"
      }
    ],
    "license_id": "CC-BY-4.0",
    "relationships_as_subject": [],
    "organization": {
      "description": "http://www.soumu.metro.tokyo.jp/\r\n\r\n所属:東京都",
      "created": "2019-11-01T03:27:19.763566",
      "title": "東京都総務局",
      "name": "t000003",
      "is_organization": true,
      "state": "active",
      "image_url": "https://catalog.data.metro.tokyo.lg.jp/tokyo_od_theme/images/organization/t000003.png",
      "revision_id": "c4e16dd4-cb3f-42dc-8be2-2eed0f9e0175",
      "type": "organization",
      "id": "5987f8a3-dfbe-4f96-b3cc-e1f3ea0a2717",
      "approval_status": "approved"
    },
    "name": "t000003d1900000005",
    "isopen": true,
    "url": "http://www.soumu.metro.tokyo.jp/02gyokaku/shijouka.html",
    "notes": "",
    "owner_org": "5987f8a3-dfbe-4f96-b3cc-e1f3ea0a2717",
    "extras": [
      {
        "key": "更新頻度",
        "value": "随時"
      }
    ],
    "license_url": "https://creativecommons.org/licenses/by/4.0/deed.ja",
    "title": "市場化テスト 過去の開催状況_資料 第1回",
    "revision_id": "e2a5978c-d6ee-41b1-a3a0-51f7c3e92cb3"
  }
}
